<?xml version="1.0" encoding="utf-8" ?><dwsync><file name="glyphicons-halflings-regular.eot" server="web4students.montgomerycollege.edu" local="3529008320" remote="3529348260" Dst="-1" /><file name="glyphicons-halflings-regular.ttf" server="web4students.montgomerycollege.edu" local="3529008320" remote="3529348260" Dst="-1" /><file name="glyphicons-halflings-regular.woff" server="web4students.montgomerycollege.edu" local="3529008320" remote="3529348260" Dst="-1" /><file name="glyphicons-halflings-regular.woff2" server="web4students.montgomerycollege.edu" local="3529008320" remote="3529348260" Dst="-1" /><file name="glyphicons-halflings-regular.eot" server="108.167.160.246//" local="3563067600" remote="3563067600" Dst="-1" /><file name="glyphicons-halflings-regular.woff2" server="108.167.160.246//" local="3563067600" remote="3563067600" Dst="-1" /><file name="glyphicons-halflings-regular.ttf" server="108.167.160.246//" local="3563067600" remote="3563067600" Dst="-1" /><file name="glyphicons-halflings-regular.woff" server="108.167.160.246//" local="3563067600" remote="3563067600" Dst="-1" /></dwsync>